{"table":[{"courses_dept":"bama","courses_id":"7445","courses_avg":80,"courses_instructor":"silk, timothy","courses_title":"brand management","courses_pass":40,"courses_fail":0,"courses_audit":0,"courses_uuid":"514"},{"courses_dept":"bama","courses_id":"7446","courses_avg":80,"courses_instructor":"","courses_title":"brand management","courses_pass":40,"courses_fail":0,"courses_audit":0,"courses_uuid":"514"},{"courses_dept":"bama","courses_id":"13315","courses_avg":83,"courses_instructor":"silk, timothy","courses_title":"brand management","courses_pass":27,"courses_fail":0,"courses_audit":0,"courses_uuid":"514"},{"courses_dept":"bama","courses_id":"13316","courses_avg":86,"courses_instructor":"silk, timothy","courses_title":"brand management","courses_pass":5,"courses_fail":0,"courses_audit":0,"courses_uuid":"514"},{"courses_dept":"bama","courses_id":"13317","courses_avg":84,"courses_instructor":"","courses_title":"brand management","courses_pass":32,"courses_fail":0,"courses_audit":0,"courses_uuid":"514"},{"courses_dept":"bama","courses_id":"22324","courses_avg":79,"courses_instructor":"stone, ann","courses_title":"brand management","courses_pass":42,"courses_fail":0,"courses_audit":0,"courses_uuid":"514"},{"courses_dept":"bama","courses_id":"22325","courses_avg":78,"courses_instructor":"low, kenton","courses_title":"brand management","courses_pass":46,"courses_fail":0,"courses_audit":0,"courses_uuid":"514"},{"courses_dept":"bama","courses_id":"22326","courses_avg":79,"courses_instructor":"","courses_title":"brand management","courses_pass":88,"courses_fail":0,"courses_audit":0,"courses_uuid":"514"},{"courses_dept":"bama","courses_id":"32835","courses_avg":80,"courses_instructor":"silk, timothy","courses_title":"brand management","courses_pass":54,"courses_fail":0,"courses_audit":0,"courses_uuid":"514"},{"courses_dept":"bama","courses_id":"32836","courses_avg":80,"courses_instructor":"","courses_title":"brand management","courses_pass":54,"courses_fail":0,"courses_audit":0,"courses_uuid":"514"},{"courses_dept":"bama","courses_id":"39699","courses_avg":80,"courses_instructor":"silk, timothy","courses_title":"brand management","courses_pass":16,"courses_fail":0,"courses_audit":0,"courses_uuid":"514"},{"courses_dept":"bama","courses_id":"39700","courses_avg":80,"courses_instructor":"silk, timothy","courses_title":"brand management","courses_pass":36,"courses_fail":0,"courses_audit":0,"courses_uuid":"514"},{"courses_dept":"bama","courses_id":"39701","courses_avg":83,"courses_instructor":"silk, timothy","courses_title":"brand management","courses_pass":27,"courses_fail":0,"courses_audit":0,"courses_uuid":"514"},{"courses_dept":"bama","courses_id":"39702","courses_avg":82,"courses_instructor":"silk, timothy","courses_title":"brand management","courses_pass":37,"courses_fail":0,"courses_audit":0,"courses_uuid":"514"},{"courses_dept":"bama","courses_id":"39703","courses_avg":83,"courses_instructor":"silk, timothy","courses_title":"brand management","courses_pass":19,"courses_fail":0,"courses_audit":0,"courses_uuid":"514"},{"courses_dept":"bama","courses_id":"39704","courses_avg":82,"courses_instructor":"","courses_title":"brand management","courses_pass":135,"courses_fail":0,"courses_audit":0,"courses_uuid":"514"},{"courses_dept":"bama","courses_id":"41824","courses_avg":80,"courses_instructor":"silk, timothy","courses_title":"brand management","courses_pass":30,"courses_fail":0,"courses_audit":0,"courses_uuid":"514"},{"courses_dept":"bama","courses_id":"41825","courses_avg":80,"courses_instructor":"silk, timothy","courses_title":"brand management","courses_pass":20,"courses_fail":0,"courses_audit":0,"courses_uuid":"514"},{"courses_dept":"bama","courses_id":"41826","courses_avg":80,"courses_instructor":"silk, timothy","courses_title":"brand management","courses_pass":26,"courses_fail":0,"courses_audit":0,"courses_uuid":"514"},{"courses_dept":"bama","courses_id":"41827","courses_avg":80,"courses_instructor":"","courses_title":"brand management","courses_pass":76,"courses_fail":0,"courses_audit":0,"courses_uuid":"514"},{"courses_dept":"bama","courses_id":"60420","courses_avg":79,"courses_instructor":"silk, timothy","courses_title":"brand management","courses_pass":15,"courses_fail":0,"courses_audit":0,"courses_uuid":"514"},{"courses_dept":"bama","courses_id":"60421","courses_avg":83,"courses_instructor":"silk, timothy","courses_title":"brand management","courses_pass":23,"courses_fail":0,"courses_audit":0,"courses_uuid":"514"},{"courses_dept":"bama","courses_id":"60422","courses_avg":82,"courses_instructor":"silk, timothy","courses_title":"brand management","courses_pass":37,"courses_fail":0,"courses_audit":0,"courses_uuid":"514"},{"courses_dept":"bama","courses_id":"60423","courses_avg":81,"courses_instructor":"silk, timothy","courses_title":"brand management","courses_pass":37,"courses_fail":0,"courses_audit":0,"courses_uuid":"514"},{"courses_dept":"bama","courses_id":"60424","courses_avg":81,"courses_instructor":"","courses_title":"brand management","courses_pass":112,"courses_fail":0,"courses_audit":0,"courses_uuid":"514"},{"courses_dept":"bama","courses_id":"60451","courses_avg":80,"courses_instructor":"silk, timothy","courses_title":"brand management","courses_pass":20,"courses_fail":0,"courses_audit":0,"courses_uuid":"514"},{"courses_dept":"bama","courses_id":"60452","courses_avg":80,"courses_instructor":"","courses_title":"brand management","courses_pass":20,"courses_fail":0,"courses_audit":0,"courses_uuid":"514"},{"courses_dept":"bama","courses_id":"63514","courses_avg":80,"courses_instructor":"zhu, juliet","courses_title":"brand management","courses_pass":28,"courses_fail":0,"courses_audit":0,"courses_uuid":"514"},{"courses_dept":"bama","courses_id":"63515","courses_avg":80,"courses_instructor":"","courses_title":"brand management","courses_pass":28,"courses_fail":0,"courses_audit":0,"courses_uuid":"514"}]}