{"table":[{"courses_dept":"chbe\r","courses_id":"7928","courses_avg":82.37,"courses_instructor":"lau, anthony k","courses_title":"air pol prv&ctrl","courses_pass":108,"courses_fail":0,"courses_audit":0,"courses_uuid":"485"},{"courses_dept":"chbe\r","courses_id":"7929","courses_avg":82.37,"courses_instructor":"","courses_title":"air pol prv&ctrl","courses_pass":108,"courses_fail":0,"courses_audit":0,"courses_uuid":"485"},{"courses_dept":"chbe\r","courses_id":"13000","courses_avg":82.13,"courses_instructor":"lau, anthony k","courses_title":"air pol prv&ctrl","courses_pass":82,"courses_fail":0,"courses_audit":0,"courses_uuid":"485"},{"courses_dept":"chbe\r","courses_id":"13001","courses_avg":82.13,"courses_instructor":"","courses_title":"air pol prv&ctrl","courses_pass":82,"courses_fail":0,"courses_audit":0,"courses_uuid":"485"},{"courses_dept":"chbe\r","courses_id":"30203","courses_avg":75.06,"courses_instructor":"bi, xiaotao","courses_title":"air pol prv&ctrl","courses_pass":51,"courses_fail":0,"courses_audit":0,"courses_uuid":"485"},{"courses_dept":"chbe\r","courses_id":"30204","courses_avg":75.06,"courses_instructor":"","courses_title":"air pol prv&ctrl","courses_pass":51,"courses_fail":0,"courses_audit":0,"courses_uuid":"485"},{"courses_dept":"chbe\r","courses_id":"45703","courses_avg":80.91,"courses_instructor":"lau, anthony k","courses_title":"air pol prv&ctrl","courses_pass":85,"courses_fail":1,"courses_audit":0,"courses_uuid":"485"},{"courses_dept":"chbe\r","courses_id":"45704","courses_avg":80.91,"courses_instructor":"","courses_title":"air pol prv&ctrl","courses_pass":85,"courses_fail":1,"courses_audit":0,"courses_uuid":"485"},{"courses_dept":"chbe\r","courses_id":"49117","courses_avg":80.99,"courses_instructor":"lau, anthony k","courses_title":"air pol prv&ctrl","courses_pass":109,"courses_fail":0,"courses_audit":0,"courses_uuid":"485"},{"courses_dept":"chbe\r","courses_id":"49118","courses_avg":80.99,"courses_instructor":"","courses_title":"air pol prv&ctrl","courses_pass":109,"courses_fail":0,"courses_audit":0,"courses_uuid":"485"},{"courses_dept":"chbe\r","courses_id":"56494","courses_avg":79.1,"courses_instructor":"lau, anthony k","courses_title":"air pol prv&ctrl","courses_pass":92,"courses_fail":0,"courses_audit":0,"courses_uuid":"485"},{"courses_dept":"chbe\r","courses_id":"56495","courses_avg":79.1,"courses_instructor":"","courses_title":"air pol prv&ctrl","courses_pass":92,"courses_fail":0,"courses_audit":0,"courses_uuid":"485"},{"courses_dept":"chbe\r","courses_id":"58605","courses_avg":79.67,"courses_instructor":"lau, anthony k","courses_title":"air pol prv&ctrl","courses_pass":82,"courses_fail":0,"courses_audit":0,"courses_uuid":"485"},{"courses_dept":"chbe\r","courses_id":"58606","courses_avg":79.67,"courses_instructor":"","courses_title":"air pol prv&ctrl","courses_pass":82,"courses_fail":0,"courses_audit":0,"courses_uuid":"485"},{"courses_dept":"chbe\r","courses_id":"63653","courses_avg":79.69,"courses_instructor":"","courses_title":"air pol prv&ctrl","courses_pass":55,"courses_fail":0,"courses_audit":0,"courses_uuid":"485"},{"courses_dept":"chbe\r","courses_id":"63654","courses_avg":79.69,"courses_instructor":"","courses_title":"air pol prv&ctrl","courses_pass":55,"courses_fail":0,"courses_audit":0,"courses_uuid":"485"},{"courses_dept":"chbe\r","courses_id":"76896","courses_avg":82.12,"courses_instructor":"lau, anthony k","courses_title":"air pol prv&ctrl","courses_pass":52,"courses_fail":0,"courses_audit":0,"courses_uuid":"485"},{"courses_dept":"chbe\r","courses_id":"76897","courses_avg":82.12,"courses_instructor":"","courses_title":"air pol prv&ctrl","courses_pass":52,"courses_fail":0,"courses_audit":0,"courses_uuid":"485"}]}