{"table":[{"courses_dept":"comm","courses_id":"38955","courses_avg":74,"courses_instructor":"yuill, garry","courses_title":"entrepren financ","courses_pass":50,"courses_fail":0,"courses_audit":0,"courses_uuid":"387"},{"courses_dept":"comm","courses_id":"38956","courses_avg":74,"courses_instructor":"","courses_title":"entrepren financ","courses_pass":50,"courses_fail":0,"courses_audit":0,"courses_uuid":"387"},{"courses_dept":"comm","courses_id":"81618","courses_avg":81,"courses_instructor":"vo, dan hieu","courses_title":"entrepren financ","courses_pass":42,"courses_fail":0,"courses_audit":0,"courses_uuid":"387"},{"courses_dept":"comm","courses_id":"81619","courses_avg":81,"courses_instructor":"","courses_title":"entrepren financ","courses_pass":42,"courses_fail":0,"courses_audit":0,"courses_uuid":"387"}]}