{"table":[{"courses_dept":"econ\r","courses_id":"11447","courses_avg":78.71,"courses_instructor":"kotwal, ashok","courses_title":"under glob","courses_pass":222,"courses_fail":3,"courses_audit":1,"courses_uuid":"255"},{"courses_dept":"econ\r","courses_id":"11448","courses_avg":78.71,"courses_instructor":"","courses_title":"under glob","courses_pass":222,"courses_fail":3,"courses_audit":1,"courses_uuid":"255"},{"courses_dept":"econ\r","courses_id":"21452","courses_avg":71.49,"courses_instructor":"drelichman, mauricio","courses_title":"under glob","courses_pass":181,"courses_fail":11,"courses_audit":0,"courses_uuid":"255"},{"courses_dept":"econ\r","courses_id":"21453","courses_avg":71.49,"courses_instructor":"","courses_title":"under glob","courses_pass":181,"courses_fail":11,"courses_audit":0,"courses_uuid":"255"},{"courses_dept":"econ\r","courses_id":"21922","courses_avg":72.04,"courses_instructor":"kotwal, ashok","courses_title":"under glob","courses_pass":135,"courses_fail":3,"courses_audit":0,"courses_uuid":"255"},{"courses_dept":"econ\r","courses_id":"21923","courses_avg":72.04,"courses_instructor":"","courses_title":"under glob","courses_pass":135,"courses_fail":3,"courses_audit":0,"courses_uuid":"255"},{"courses_dept":"econ\r","courses_id":"51724","courses_avg":72.45,"courses_instructor":"drelichman, mauricio","courses_title":"under glob","courses_pass":65,"courses_fail":2,"courses_audit":0,"courses_uuid":"255"},{"courses_dept":"econ\r","courses_id":"51725","courses_avg":72.45,"courses_instructor":"","courses_title":"under glob","courses_pass":65,"courses_fail":2,"courses_audit":0,"courses_uuid":"255"},{"courses_dept":"econ\r","courses_id":"52257","courses_avg":73.12,"courses_instructor":"drelichman, mauricio","courses_title":"under glob","courses_pass":189,"courses_fail":2,"courses_audit":0,"courses_uuid":"255"},{"courses_dept":"econ\r","courses_id":"52258","courses_avg":73.12,"courses_instructor":"","courses_title":"under glob","courses_pass":189,"courses_fail":2,"courses_audit":0,"courses_uuid":"255"},{"courses_dept":"econ\r","courses_id":"58342","courses_avg":68.76,"courses_instructor":"kotwal, ashok","courses_title":"under glob","courses_pass":188,"courses_fail":10,"courses_audit":0,"courses_uuid":"255"},{"courses_dept":"econ\r","courses_id":"58343","courses_avg":68.76,"courses_instructor":"","courses_title":"under glob","courses_pass":188,"courses_fail":10,"courses_audit":0,"courses_uuid":"255"},{"courses_dept":"econ\r","courses_id":"69800","courses_avg":74.72,"courses_instructor":"","courses_title":"under glob","courses_pass":216,"courses_fail":6,"courses_audit":0,"courses_uuid":"255"},{"courses_dept":"econ\r","courses_id":"69801","courses_avg":74.72,"courses_instructor":"","courses_title":"under glob","courses_pass":216,"courses_fail":6,"courses_audit":0,"courses_uuid":"255"},{"courses_dept":"econ\r","courses_id":"74308","courses_avg":76.94,"courses_instructor":"drelichman, mauricio","courses_title":"under glob","courses_pass":173,"courses_fail":5,"courses_audit":0,"courses_uuid":"255"},{"courses_dept":"econ\r","courses_id":"74309","courses_avg":83.11,"courses_instructor":"kotwal, ashok","courses_title":"under glob","courses_pass":79,"courses_fail":0,"courses_audit":0,"courses_uuid":"255"},{"courses_dept":"econ\r","courses_id":"74310","courses_avg":78.84,"courses_instructor":"","courses_title":"under glob","courses_pass":252,"courses_fail":5,"courses_audit":0,"courses_uuid":"255"},{"courses_dept":"econ\r","courses_id":"78358","courses_avg":71.85,"courses_instructor":"kotwal, ashok","courses_title":"under glob","courses_pass":152,"courses_fail":4,"courses_audit":0,"courses_uuid":"255"},{"courses_dept":"econ\r","courses_id":"78359","courses_avg":71.85,"courses_instructor":"","courses_title":"under glob","courses_pass":152,"courses_fail":4,"courses_audit":0,"courses_uuid":"255"},{"courses_dept":"econ\r","courses_id":"90908","courses_avg":72.03,"courses_instructor":"kotwal, ashok","courses_title":"under glob","courses_pass":144,"courses_fail":8,"courses_audit":0,"courses_uuid":"255"},{"courses_dept":"econ\r","courses_id":"90909","courses_avg":72.03,"courses_instructor":"","courses_title":"under glob","courses_pass":144,"courses_fail":8,"courses_audit":0,"courses_uuid":"255"}]}