{"table":[{"courses_dept":"eosc","courses_id":"2537","courses_avg":91,"courses_instructor":"bostock, michael","courses_title":"mech erth quake","courses_pass":8,"courses_fail":0,"courses_audit":0,"courses_uuid":"562"},{"courses_dept":"eosc","courses_id":"2538","courses_avg":91,"courses_instructor":"","courses_title":"mech erth quake","courses_pass":8,"courses_fail":0,"courses_audit":0,"courses_uuid":"562"},{"courses_dept":"eosc","courses_id":"38679","courses_avg":86,"courses_instructor":"hearn, elizabeth","courses_title":"mech erth quake","courses_pass":3,"courses_fail":0,"courses_audit":2,"courses_uuid":"562"},{"courses_dept":"eosc","courses_id":"38680","courses_avg":86,"courses_instructor":"","courses_title":"mech erth quake","courses_pass":3,"courses_fail":0,"courses_audit":2,"courses_uuid":"562"},{"courses_dept":"eosc","courses_id":"70697","courses_avg":90,"courses_instructor":"bostock, michael","courses_title":"mech erth quake","courses_pass":8,"courses_fail":0,"courses_audit":2,"courses_uuid":"562"},{"courses_dept":"eosc","courses_id":"70698","courses_avg":90,"courses_instructor":"","courses_title":"mech erth quake","courses_pass":8,"courses_fail":0,"courses_audit":2,"courses_uuid":"562"}]}