{"table":[{"courses_dept":"eosc","courses_id":"2533","courses_avg":86,"courses_instructor":"eberhardt, erik","courses_title":"tnl&undergrd eng","courses_pass":22,"courses_fail":0,"courses_audit":0,"courses_uuid":"547"},{"courses_dept":"eosc","courses_id":"2534","courses_avg":86,"courses_instructor":"","courses_title":"tnl&undergrd eng","courses_pass":22,"courses_fail":0,"courses_audit":0,"courses_uuid":"547"},{"courses_dept":"eosc","courses_id":"17844","courses_avg":87,"courses_instructor":"eberhardt, erik","courses_title":"tnl&undergrd eng","courses_pass":16,"courses_fail":0,"courses_audit":0,"courses_uuid":"547"},{"courses_dept":"eosc","courses_id":"17845","courses_avg":87,"courses_instructor":"","courses_title":"tnl&undergrd eng","courses_pass":16,"courses_fail":0,"courses_audit":0,"courses_uuid":"547"},{"courses_dept":"eosc","courses_id":"46113","courses_avg":87,"courses_instructor":"eberhardt, erik","courses_title":"tnl&undergrd eng","courses_pass":19,"courses_fail":0,"courses_audit":0,"courses_uuid":"547"},{"courses_dept":"eosc","courses_id":"46114","courses_avg":87,"courses_instructor":"","courses_title":"tnl&undergrd eng","courses_pass":19,"courses_fail":0,"courses_audit":0,"courses_uuid":"547"},{"courses_dept":"eosc","courses_id":"69039","courses_avg":86,"courses_instructor":"eberhardt, erik","courses_title":"tnl&undergrd eng","courses_pass":17,"courses_fail":0,"courses_audit":0,"courses_uuid":"547"},{"courses_dept":"eosc","courses_id":"69040","courses_avg":86,"courses_instructor":"","courses_title":"tnl&undergrd eng","courses_pass":17,"courses_fail":0,"courses_audit":0,"courses_uuid":"547"},{"courses_dept":"eosc","courses_id":"70695","courses_avg":85,"courses_instructor":"eberhardt, erik","courses_title":"tnl&undergrd eng","courses_pass":16,"courses_fail":0,"courses_audit":0,"courses_uuid":"547"},{"courses_dept":"eosc","courses_id":"70696","courses_avg":85,"courses_instructor":"","courses_title":"tnl&undergrd eng","courses_pass":16,"courses_fail":0,"courses_audit":0,"courses_uuid":"547"},{"courses_dept":"eosc","courses_id":"79240","courses_avg":88,"courses_instructor":"eberhardt, erik","courses_title":"tnl&undergrd eng","courses_pass":10,"courses_fail":0,"courses_audit":0,"courses_uuid":"547"},{"courses_dept":"eosc","courses_id":"79241","courses_avg":88,"courses_instructor":"","courses_title":"tnl&undergrd eng","courses_pass":10,"courses_fail":0,"courses_audit":0,"courses_uuid":"547"},{"courses_dept":"eosc","courses_id":"82974","courses_avg":86,"courses_instructor":"","courses_title":"tnl&undergrd eng","courses_pass":8,"courses_fail":0,"courses_audit":0,"courses_uuid":"547"},{"courses_dept":"eosc","courses_id":"82975","courses_avg":86,"courses_instructor":"","courses_title":"tnl&undergrd eng","courses_pass":8,"courses_fail":0,"courses_audit":0,"courses_uuid":"547"},{"courses_dept":"eosc","courses_id":"86470","courses_avg":86,"courses_instructor":"eberhardt, erik","courses_title":"tnl&undergrd eng","courses_pass":16,"courses_fail":0,"courses_audit":0,"courses_uuid":"547"},{"courses_dept":"eosc","courses_id":"86471","courses_avg":86,"courses_instructor":"","courses_title":"tnl&undergrd eng","courses_pass":16,"courses_fail":0,"courses_audit":0,"courses_uuid":"547"}]}