{"table":[{"courses_dept":"epse","courses_id":"3163","courses_avg":91,"courses_instructor":"el khatib, lara","courses_title":"typ atyp inf/ch","courses_pass":48,"courses_fail":0,"courses_audit":0,"courses_uuid":"406"},{"courses_dept":"epse","courses_id":"3164","courses_avg":91,"courses_instructor":"el khatib, lara","courses_title":"typ atyp inf/ch","courses_pass":44,"courses_fail":0,"courses_audit":0,"courses_uuid":"406"},{"courses_dept":"epse","courses_id":"3165","courses_avg":91,"courses_instructor":"","courses_title":"typ atyp inf/ch","courses_pass":92,"courses_fail":0,"courses_audit":0,"courses_uuid":"406"},{"courses_dept":"epse","courses_id":"6300","courses_avg":90,"courses_instructor":"el khatib, lara","courses_title":"typ atyp inf/ch","courses_pass":58,"courses_fail":1,"courses_audit":0,"courses_uuid":"406"},{"courses_dept":"epse","courses_id":"6301","courses_avg":93,"courses_instructor":"el khatib, lara","courses_title":"typ atyp inf/ch","courses_pass":57,"courses_fail":0,"courses_audit":0,"courses_uuid":"406"},{"courses_dept":"epse","courses_id":"6302","courses_avg":92,"courses_instructor":"","courses_title":"typ atyp inf/ch","courses_pass":115,"courses_fail":1,"courses_audit":0,"courses_uuid":"406"},{"courses_dept":"epse","courses_id":"13117","courses_avg":93,"courses_instructor":"el khatib, lara","courses_title":"typ atyp inf/ch","courses_pass":67,"courses_fail":0,"courses_audit":0,"courses_uuid":"406"},{"courses_dept":"epse","courses_id":"13118","courses_avg":93,"courses_instructor":"","courses_title":"typ atyp inf/ch","courses_pass":67,"courses_fail":0,"courses_audit":0,"courses_uuid":"406"},{"courses_dept":"epse","courses_id":"28925","courses_avg":90,"courses_instructor":"cox, elizabeth;reiner, ann","courses_title":"typ atyp inf/ch","courses_pass":33,"courses_fail":0,"courses_audit":0,"courses_uuid":"406"},{"courses_dept":"epse","courses_id":"28926","courses_avg":86,"courses_instructor":"graves, carolyn;reiner, ann","courses_title":"typ atyp inf/ch","courses_pass":36,"courses_fail":0,"courses_audit":0,"courses_uuid":"406"},{"courses_dept":"epse","courses_id":"28927","courses_avg":88,"courses_instructor":"","courses_title":"typ atyp inf/ch","courses_pass":69,"courses_fail":0,"courses_audit":0,"courses_uuid":"406"},{"courses_dept":"epse","courses_id":"29235","courses_avg":94,"courses_instructor":"el khatib, lara","courses_title":"typ atyp inf/ch","courses_pass":43,"courses_fail":0,"courses_audit":0,"courses_uuid":"406"},{"courses_dept":"epse","courses_id":"29236","courses_avg":90,"courses_instructor":"el khatib, lara","courses_title":"typ atyp inf/ch","courses_pass":39,"courses_fail":0,"courses_audit":0,"courses_uuid":"406"},{"courses_dept":"epse","courses_id":"29237","courses_avg":92,"courses_instructor":"","courses_title":"typ atyp inf/ch","courses_pass":82,"courses_fail":0,"courses_audit":0,"courses_uuid":"406"},{"courses_dept":"epse","courses_id":"35864","courses_avg":90,"courses_instructor":"el khatib, lara","courses_title":"typ atyp inf/ch","courses_pass":27,"courses_fail":0,"courses_audit":0,"courses_uuid":"406"},{"courses_dept":"epse","courses_id":"35865","courses_avg":90,"courses_instructor":"","courses_title":"typ atyp inf/ch","courses_pass":27,"courses_fail":0,"courses_audit":0,"courses_uuid":"406"},{"courses_dept":"epse","courses_id":"38137","courses_avg":92,"courses_instructor":"el khatib, lara","courses_title":"typ atyp inf/ch","courses_pass":64,"courses_fail":0,"courses_audit":0,"courses_uuid":"406"},{"courses_dept":"epse","courses_id":"38138","courses_avg":92,"courses_instructor":"el khatib, lara","courses_title":"typ atyp inf/ch","courses_pass":75,"courses_fail":2,"courses_audit":0,"courses_uuid":"406"},{"courses_dept":"epse","courses_id":"38139","courses_avg":92,"courses_instructor":"","courses_title":"typ atyp inf/ch","courses_pass":139,"courses_fail":2,"courses_audit":0,"courses_uuid":"406"},{"courses_dept":"epse","courses_id":"44384","courses_avg":91,"courses_instructor":"el khatib, lara","courses_title":"typ atyp inf/ch","courses_pass":59,"courses_fail":0,"courses_audit":0,"courses_uuid":"406"},{"courses_dept":"epse","courses_id":"44385","courses_avg":91,"courses_instructor":"","courses_title":"typ atyp inf/ch","courses_pass":59,"courses_fail":0,"courses_audit":0,"courses_uuid":"406"},{"courses_dept":"epse","courses_id":"44798","courses_avg":92,"courses_instructor":"el khatib, lara","courses_title":"typ atyp inf/ch","courses_pass":29,"courses_fail":0,"courses_audit":0,"courses_uuid":"406"},{"courses_dept":"epse","courses_id":"44799","courses_avg":92,"courses_instructor":"","courses_title":"typ atyp inf/ch","courses_pass":29,"courses_fail":0,"courses_audit":0,"courses_uuid":"406"},{"courses_dept":"epse","courses_id":"49642","courses_avg":90,"courses_instructor":"el khatib, lara","courses_title":"typ atyp inf/ch","courses_pass":35,"courses_fail":0,"courses_audit":0,"courses_uuid":"406"},{"courses_dept":"epse","courses_id":"49643","courses_avg":90,"courses_instructor":"","courses_title":"typ atyp inf/ch","courses_pass":35,"courses_fail":0,"courses_audit":0,"courses_uuid":"406"},{"courses_dept":"epse","courses_id":"56537","courses_avg":91,"courses_instructor":"el khatib, lara","courses_title":"typ atyp inf/ch","courses_pass":49,"courses_fail":0,"courses_audit":0,"courses_uuid":"406"},{"courses_dept":"epse","courses_id":"56538","courses_avg":91,"courses_instructor":"","courses_title":"typ atyp inf/ch","courses_pass":49,"courses_fail":0,"courses_audit":0,"courses_uuid":"406"},{"courses_dept":"epse","courses_id":"61381","courses_avg":90,"courses_instructor":"cox, elizabeth;reiner, ann","courses_title":"typ atyp inf/ch","courses_pass":33,"courses_fail":0,"courses_audit":0,"courses_uuid":"406"},{"courses_dept":"epse","courses_id":"61382","courses_avg":86,"courses_instructor":"graves, carolyn;reiner, ann","courses_title":"typ atyp inf/ch","courses_pass":36,"courses_fail":1,"courses_audit":0,"courses_uuid":"406"},{"courses_dept":"epse","courses_id":"61383","courses_avg":88,"courses_instructor":"","courses_title":"typ atyp inf/ch","courses_pass":69,"courses_fail":1,"courses_audit":0,"courses_uuid":"406"},{"courses_dept":"epse","courses_id":"76246","courses_avg":88,"courses_instructor":"cox, elizabeth;reiner, ann","courses_title":"typ atyp inf/ch","courses_pass":27,"courses_fail":1,"courses_audit":0,"courses_uuid":"406"},{"courses_dept":"epse","courses_id":"76247","courses_avg":86,"courses_instructor":"graves, carolyn;reiner, ann","courses_title":"typ atyp inf/ch","courses_pass":27,"courses_fail":0,"courses_audit":0,"courses_uuid":"406"},{"courses_dept":"epse","courses_id":"76248","courses_avg":87,"courses_instructor":"","courses_title":"typ atyp inf/ch","courses_pass":54,"courses_fail":1,"courses_audit":0,"courses_uuid":"406"},{"courses_dept":"epse","courses_id":"86873","courses_avg":81,"courses_instructor":"phillips, lynda","courses_title":"typ atyp inf/ch","courses_pass":20,"courses_fail":1,"courses_audit":0,"courses_uuid":"406"},{"courses_dept":"epse","courses_id":"86874","courses_avg":84,"courses_instructor":"phillips, lynda","courses_title":"typ atyp inf/ch","courses_pass":19,"courses_fail":1,"courses_audit":0,"courses_uuid":"406"},{"courses_dept":"epse","courses_id":"86875","courses_avg":83,"courses_instructor":"","courses_title":"typ atyp inf/ch","courses_pass":39,"courses_fail":2,"courses_audit":0,"courses_uuid":"406"}]}