{"table":[{"courses_dept":"fnh\r","courses_id":"6642","courses_avg":85.06,"courses_instructor":"","courses_title":"food law reg qua","courses_pass":72,"courses_fail":0,"courses_audit":0,"courses_uuid":"403"},{"courses_dept":"fnh\r","courses_id":"6643","courses_avg":85.06,"courses_instructor":"","courses_title":"food law reg qua","courses_pass":72,"courses_fail":0,"courses_audit":0,"courses_uuid":"403"},{"courses_dept":"fnh\r","courses_id":"11764","courses_avg":80.56,"courses_instructor":"","courses_title":"food law reg qua","courses_pass":71,"courses_fail":0,"courses_audit":0,"courses_uuid":"403"},{"courses_dept":"fnh\r","courses_id":"11765","courses_avg":80.56,"courses_instructor":"","courses_title":"food law reg qua","courses_pass":71,"courses_fail":0,"courses_audit":0,"courses_uuid":"403"},{"courses_dept":"fnh\r","courses_id":"14030","courses_avg":82.64,"courses_instructor":"","courses_title":"food law reg qua","courses_pass":73,"courses_fail":0,"courses_audit":0,"courses_uuid":"403"},{"courses_dept":"fnh\r","courses_id":"14031","courses_avg":82.64,"courses_instructor":"","courses_title":"food law reg qua","courses_pass":73,"courses_fail":0,"courses_audit":0,"courses_uuid":"403"},{"courses_dept":"fnh\r","courses_id":"23625","courses_avg":82.31,"courses_instructor":"","courses_title":"food law reg qua","courses_pass":72,"courses_fail":0,"courses_audit":0,"courses_uuid":"403"},{"courses_dept":"fnh\r","courses_id":"23626","courses_avg":82.31,"courses_instructor":"","courses_title":"food law reg qua","courses_pass":72,"courses_fail":0,"courses_audit":0,"courses_uuid":"403"},{"courses_dept":"fnh\r","courses_id":"51646","courses_avg":86.21,"courses_instructor":"","courses_title":"food law reg qua","courses_pass":72,"courses_fail":0,"courses_audit":0,"courses_uuid":"403"},{"courses_dept":"fnh\r","courses_id":"51647","courses_avg":86.21,"courses_instructor":"","courses_title":"food law reg qua","courses_pass":72,"courses_fail":0,"courses_audit":0,"courses_uuid":"403"},{"courses_dept":"fnh\r","courses_id":"65040","courses_avg":80.92,"courses_instructor":"","courses_title":"food law reg qua","courses_pass":59,"courses_fail":0,"courses_audit":0,"courses_uuid":"403"},{"courses_dept":"fnh\r","courses_id":"65041","courses_avg":80.92,"courses_instructor":"","courses_title":"food law reg qua","courses_pass":59,"courses_fail":0,"courses_audit":0,"courses_uuid":"403"},{"courses_dept":"fnh\r","courses_id":"68394","courses_avg":81.08,"courses_instructor":"","courses_title":"food law reg qua","courses_pass":78,"courses_fail":0,"courses_audit":0,"courses_uuid":"403"},{"courses_dept":"fnh\r","courses_id":"68395","courses_avg":81.08,"courses_instructor":"","courses_title":"food law reg qua","courses_pass":78,"courses_fail":0,"courses_audit":0,"courses_uuid":"403"},{"courses_dept":"fnh\r","courses_id":"68794","courses_avg":82.29,"courses_instructor":"","courses_title":"food law reg qua","courses_pass":69,"courses_fail":0,"courses_audit":0,"courses_uuid":"403"},{"courses_dept":"fnh\r","courses_id":"68795","courses_avg":82.29,"courses_instructor":"","courses_title":"food law reg qua","courses_pass":69,"courses_fail":0,"courses_audit":0,"courses_uuid":"403"},{"courses_dept":"fnh\r","courses_id":"75686","courses_avg":81.64,"courses_instructor":"","courses_title":"food law reg qua","courses_pass":69,"courses_fail":0,"courses_audit":0,"courses_uuid":"403"},{"courses_dept":"fnh\r","courses_id":"75687","courses_avg":81.64,"courses_instructor":"","courses_title":"food law reg qua","courses_pass":69,"courses_fail":0,"courses_audit":0,"courses_uuid":"403"}]}