{"table":[{"courses_dept":"fopr\r","courses_id":"6798","courses_avg":68,"courses_instructor":"alila, younes","courses_title":"anl mthd frst hy","courses_pass":6,"courses_fail":0,"courses_audit":0,"courses_uuid":"388"},{"courses_dept":"fopr\r","courses_id":"6799","courses_avg":68,"courses_instructor":"","courses_title":"anl mthd frst hy","courses_pass":6,"courses_fail":0,"courses_audit":0,"courses_uuid":"388"},{"courses_dept":"fopr\r","courses_id":"8666","courses_avg":61.53,"courses_instructor":"alila, younes","courses_title":"anl mthd frst hy","courses_pass":14,"courses_fail":1,"courses_audit":0,"courses_uuid":"388"},{"courses_dept":"fopr\r","courses_id":"8667","courses_avg":61.53,"courses_instructor":"","courses_title":"anl mthd frst hy","courses_pass":14,"courses_fail":1,"courses_audit":0,"courses_uuid":"388"},{"courses_dept":"fopr\r","courses_id":"15530","courses_avg":64.8,"courses_instructor":"alila, younes","courses_title":"anl mthd frst hy","courses_pass":4,"courses_fail":1,"courses_audit":0,"courses_uuid":"388"},{"courses_dept":"fopr\r","courses_id":"15531","courses_avg":64.8,"courses_instructor":"","courses_title":"anl mthd frst hy","courses_pass":4,"courses_fail":1,"courses_audit":0,"courses_uuid":"388"},{"courses_dept":"fopr\r","courses_id":"22967","courses_avg":70.14,"courses_instructor":"alila, younes","courses_title":"anl mthd frst hy","courses_pass":6,"courses_fail":1,"courses_audit":0,"courses_uuid":"388"},{"courses_dept":"fopr\r","courses_id":"22968","courses_avg":70.14,"courses_instructor":"","courses_title":"anl mthd frst hy","courses_pass":6,"courses_fail":1,"courses_audit":0,"courses_uuid":"388"},{"courses_dept":"fopr\r","courses_id":"45869","courses_avg":64.57,"courses_instructor":"alila, younes","courses_title":"anl mthd frst hy","courses_pass":14,"courses_fail":0,"courses_audit":0,"courses_uuid":"388"},{"courses_dept":"fopr\r","courses_id":"45870","courses_avg":64.57,"courses_instructor":"","courses_title":"anl mthd frst hy","courses_pass":14,"courses_fail":0,"courses_audit":0,"courses_uuid":"388"},{"courses_dept":"fopr\r","courses_id":"48625","courses_avg":76.7,"courses_instructor":"varhola troya, andres","courses_title":"anl mthd frst hy","courses_pass":10,"courses_fail":0,"courses_audit":0,"courses_uuid":"388"},{"courses_dept":"fopr\r","courses_id":"48626","courses_avg":76.7,"courses_instructor":"","courses_title":"anl mthd frst hy","courses_pass":10,"courses_fail":0,"courses_audit":0,"courses_uuid":"388"},{"courses_dept":"fopr\r","courses_id":"56382","courses_avg":65.93,"courses_instructor":"alila, younes","courses_title":"anl mthd frst hy","courses_pass":14,"courses_fail":1,"courses_audit":0,"courses_uuid":"388"},{"courses_dept":"fopr\r","courses_id":"56383","courses_avg":65.93,"courses_instructor":"","courses_title":"anl mthd frst hy","courses_pass":14,"courses_fail":1,"courses_audit":0,"courses_uuid":"388"},{"courses_dept":"fopr\r","courses_id":"59157","courses_avg":69.6,"courses_instructor":"","courses_title":"anl mthd frst hy","courses_pass":10,"courses_fail":0,"courses_audit":0,"courses_uuid":"388"},{"courses_dept":"fopr\r","courses_id":"59158","courses_avg":69.6,"courses_instructor":"","courses_title":"anl mthd frst hy","courses_pass":10,"courses_fail":0,"courses_audit":0,"courses_uuid":"388"},{"courses_dept":"fopr\r","courses_id":"84115","courses_avg":66.67,"courses_instructor":"alila, younes","courses_title":"anl mthd frst hy","courses_pass":6,"courses_fail":0,"courses_audit":0,"courses_uuid":"388"},{"courses_dept":"fopr\r","courses_id":"84116","courses_avg":66.67,"courses_instructor":"","courses_title":"anl mthd frst hy","courses_pass":6,"courses_fail":0,"courses_audit":0,"courses_uuid":"388"},{"courses_dept":"fopr\r","courses_id":"84771","courses_avg":72.17,"courses_instructor":"varhola troya, andres","courses_title":"anl mthd frst hy","courses_pass":12,"courses_fail":0,"courses_audit":0,"courses_uuid":"388"},{"courses_dept":"fopr\r","courses_id":"84772","courses_avg":72.17,"courses_instructor":"","courses_title":"anl mthd frst hy","courses_pass":12,"courses_fail":0,"courses_audit":0,"courses_uuid":"388"}]}