{"table":[{"courses_dept":"fren\r","courses_id":"1677","courses_avg":76.26,"courses_instructor":"","courses_title":"fren lang&lit i","courses_pass":19,"courses_fail":0,"courses_audit":0,"courses_uuid":"122"},{"courses_dept":"fren\r","courses_id":"1678","courses_avg":76.26,"courses_instructor":"","courses_title":"fren lang&lit i","courses_pass":19,"courses_fail":0,"courses_audit":0,"courses_uuid":"122"},{"courses_dept":"fren\r","courses_id":"20839","courses_avg":74.36,"courses_instructor":"scott, anne","courses_title":"fren lang&lit i","courses_pass":25,"courses_fail":0,"courses_audit":0,"courses_uuid":"122"},{"courses_dept":"fren\r","courses_id":"20840","courses_avg":74.36,"courses_instructor":"","courses_title":"fren lang&lit i","courses_pass":25,"courses_fail":0,"courses_audit":0,"courses_uuid":"122"},{"courses_dept":"fren\r","courses_id":"27001","courses_avg":71.72,"courses_instructor":"bodolec, jacques","courses_title":"fren lang&lit i","courses_pass":17,"courses_fail":1,"courses_audit":0,"courses_uuid":"122"},{"courses_dept":"fren\r","courses_id":"27002","courses_avg":77.44,"courses_instructor":"miller, robert","courses_title":"fren lang&lit i","courses_pass":27,"courses_fail":0,"courses_audit":0,"courses_uuid":"122"},{"courses_dept":"fren\r","courses_id":"27003","courses_avg":73.09,"courses_instructor":"onyeoziri-miller, gloria","courses_title":"fren lang&lit i","courses_pass":22,"courses_fail":0,"courses_audit":0,"courses_uuid":"122"},{"courses_dept":"fren\r","courses_id":"27004","courses_avg":73.35,"courses_instructor":"o'hagan, michael","courses_title":"fren lang&lit i","courses_pass":17,"courses_fail":0,"courses_audit":0,"courses_uuid":"122"},{"courses_dept":"fren\r","courses_id":"27005","courses_avg":72.11,"courses_instructor":"scott, anne","courses_title":"fren lang&lit i","courses_pass":28,"courses_fail":0,"courses_audit":0,"courses_uuid":"122"},{"courses_dept":"fren\r","courses_id":"27006","courses_avg":75.32,"courses_instructor":"godfrey, sima","courses_title":"fren lang&lit i","courses_pass":25,"courses_fail":0,"courses_audit":0,"courses_uuid":"122"},{"courses_dept":"fren\r","courses_id":"27007","courses_avg":76.38,"courses_instructor":"laroussi, farid","courses_title":"fren lang&lit i","courses_pass":24,"courses_fail":0,"courses_audit":0,"courses_uuid":"122"},{"courses_dept":"fren\r","courses_id":"27008","courses_avg":73.29,"courses_instructor":"simpson, anne","courses_title":"fren lang&lit i","courses_pass":27,"courses_fail":1,"courses_audit":0,"courses_uuid":"122"},{"courses_dept":"fren\r","courses_id":"27009","courses_avg":68.36,"courses_instructor":"winder, william","courses_title":"fren lang&lit i","courses_pass":24,"courses_fail":1,"courses_audit":0,"courses_uuid":"122"},{"courses_dept":"fren\r","courses_id":"27010","courses_avg":76.65,"courses_instructor":"culbert, john","courses_title":"fren lang&lit i","courses_pass":19,"courses_fail":1,"courses_audit":0,"courses_uuid":"122"},{"courses_dept":"fren\r","courses_id":"27011","courses_avg":82.1,"courses_instructor":"miller, robert;romengo, margherita;scott, anne","courses_title":"fren lang&lit i","courses_pass":20,"courses_fail":0,"courses_audit":0,"courses_uuid":"122"},{"courses_dept":"fren\r","courses_id":"27012","courses_avg":74.44,"courses_instructor":"","courses_title":"fren lang&lit i","courses_pass":250,"courses_fail":4,"courses_audit":0,"courses_uuid":"122"},{"courses_dept":"fren\r","courses_id":"52901","courses_avg":75.07,"courses_instructor":"kamranian, somayeh","courses_title":"fren lang&lit i","courses_pass":28,"courses_fail":0,"courses_audit":0,"courses_uuid":"122"},{"courses_dept":"fren\r","courses_id":"52902","courses_avg":68.09,"courses_instructor":"onyeoziri-miller, gloria","courses_title":"fren lang&lit i","courses_pass":20,"courses_fail":2,"courses_audit":0,"courses_uuid":"122"},{"courses_dept":"fren\r","courses_id":"52903","courses_avg":72.69,"courses_instructor":"palisse, stephanie","courses_title":"fren lang&lit i","courses_pass":29,"courses_fail":0,"courses_audit":0,"courses_uuid":"122"},{"courses_dept":"fren\r","courses_id":"52904","courses_avg":73.28,"courses_instructor":"scott, anne","courses_title":"fren lang&lit i","courses_pass":28,"courses_fail":1,"courses_audit":0,"courses_uuid":"122"},{"courses_dept":"fren\r","courses_id":"52905","courses_avg":75.67,"courses_instructor":"palisse, stephanie","courses_title":"fren lang&lit i","courses_pass":23,"courses_fail":1,"courses_audit":0,"courses_uuid":"122"},{"courses_dept":"fren\r","courses_id":"52906","courses_avg":75.43,"courses_instructor":"miller, robert","courses_title":"fren lang&lit i","courses_pass":27,"courses_fail":1,"courses_audit":0,"courses_uuid":"122"},{"courses_dept":"fren\r","courses_id":"52907","courses_avg":72.04,"courses_instructor":"winder, william","courses_title":"fren lang&lit i","courses_pass":22,"courses_fail":1,"courses_audit":0,"courses_uuid":"122"},{"courses_dept":"fren\r","courses_id":"52908","courses_avg":74.88,"courses_instructor":"hodgson, richard","courses_title":"fren lang&lit i","courses_pass":15,"courses_fail":1,"courses_audit":0,"courses_uuid":"122"},{"courses_dept":"fren\r","courses_id":"52909","courses_avg":75.37,"courses_instructor":"","courses_title":"fren lang&lit i","courses_pass":30,"courses_fail":0,"courses_audit":0,"courses_uuid":"122"},{"courses_dept":"fren\r","courses_id":"52910","courses_avg":73.7,"courses_instructor":"","courses_title":"fren lang&lit i","courses_pass":222,"courses_fail":7,"courses_audit":0,"courses_uuid":"122"},{"courses_dept":"fren\r","courses_id":"53002","courses_avg":76.81,"courses_instructor":"miller, robert","courses_title":"fren lang&lit i","courses_pass":26,"courses_fail":0,"courses_audit":1,"courses_uuid":"122"},{"courses_dept":"fren\r","courses_id":"53003","courses_avg":76.81,"courses_instructor":"","courses_title":"fren lang&lit i","courses_pass":26,"courses_fail":0,"courses_audit":1,"courses_uuid":"122"},{"courses_dept":"fren\r","courses_id":"58208","courses_avg":74.72,"courses_instructor":"miller, robert","courses_title":"fren lang&lit i","courses_pass":23,"courses_fail":2,"courses_audit":0,"courses_uuid":"122"},{"courses_dept":"fren\r","courses_id":"58209","courses_avg":67.5,"courses_instructor":"o'hagan, michael","courses_title":"fren lang&lit i","courses_pass":18,"courses_fail":2,"courses_audit":0,"courses_uuid":"122"},{"courses_dept":"fren\r","courses_id":"58210","courses_avg":72.96,"courses_instructor":"onyeoziri-miller, gloria","courses_title":"fren lang&lit i","courses_pass":26,"courses_fail":0,"courses_audit":0,"courses_uuid":"122"},{"courses_dept":"fren\r","courses_id":"58211","courses_avg":74.69,"courses_instructor":"scott, anne","courses_title":"fren lang&lit i","courses_pass":29,"courses_fail":0,"courses_audit":0,"courses_uuid":"122"},{"courses_dept":"fren\r","courses_id":"58212","courses_avg":76.32,"courses_instructor":"scott, anne","courses_title":"fren lang&lit i","courses_pass":25,"courses_fail":0,"courses_audit":0,"courses_uuid":"122"},{"courses_dept":"fren\r","courses_id":"58213","courses_avg":74.58,"courses_instructor":"simpson, anne","courses_title":"fren lang&lit i","courses_pass":24,"courses_fail":0,"courses_audit":0,"courses_uuid":"122"},{"courses_dept":"fren\r","courses_id":"58214","courses_avg":71.35,"courses_instructor":"o'brien, juliet","courses_title":"fren lang&lit i","courses_pass":25,"courses_fail":1,"courses_audit":0,"courses_uuid":"122"},{"courses_dept":"fren\r","courses_id":"58215","courses_avg":74.32,"courses_instructor":"scott, anne;tba","courses_title":"fren lang&lit i","courses_pass":27,"courses_fail":1,"courses_audit":1,"courses_uuid":"122"},{"courses_dept":"fren\r","courses_id":"58216","courses_avg":72.05,"courses_instructor":"culbert, john","courses_title":"fren lang&lit i","courses_pass":21,"courses_fail":1,"courses_audit":0,"courses_uuid":"122"},{"courses_dept":"fren\r","courses_id":"58217","courses_avg":73.33,"courses_instructor":"","courses_title":"fren lang&lit i","courses_pass":218,"courses_fail":7,"courses_audit":1,"courses_uuid":"122"},{"courses_dept":"fren\r","courses_id":"58793","courses_avg":71.81,"courses_instructor":"palisse, stephanie","courses_title":"fren lang&lit i","courses_pass":25,"courses_fail":2,"courses_audit":0,"courses_uuid":"122"},{"courses_dept":"fren\r","courses_id":"58794","courses_avg":74.74,"courses_instructor":"miller, robert","courses_title":"fren lang&lit i","courses_pass":26,"courses_fail":1,"courses_audit":1,"courses_uuid":"122"},{"courses_dept":"fren\r","courses_id":"58795","courses_avg":75.87,"courses_instructor":"palisse, stephanie","courses_title":"fren lang&lit i","courses_pass":23,"courses_fail":0,"courses_audit":0,"courses_uuid":"122"},{"courses_dept":"fren\r","courses_id":"58796","courses_avg":72.56,"courses_instructor":"phan, chantal","courses_title":"fren lang&lit i","courses_pass":9,"courses_fail":0,"courses_audit":0,"courses_uuid":"122"},{"courses_dept":"fren\r","courses_id":"58797","courses_avg":76.38,"courses_instructor":"","courses_title":"fren lang&lit i","courses_pass":29,"courses_fail":0,"courses_audit":1,"courses_uuid":"122"},{"courses_dept":"fren\r","courses_id":"58798","courses_avg":73.96,"courses_instructor":"scott, anne","courses_title":"fren lang&lit i","courses_pass":28,"courses_fail":0,"courses_audit":0,"courses_uuid":"122"},{"courses_dept":"fren\r","courses_id":"58799","courses_avg":70.92,"courses_instructor":"scott, anne","courses_title":"fren lang&lit i","courses_pass":26,"courses_fail":0,"courses_audit":0,"courses_uuid":"122"},{"courses_dept":"fren\r","courses_id":"58800","courses_avg":84.2,"courses_instructor":"hodgson, richard","courses_title":"fren lang&lit i","courses_pass":15,"courses_fail":0,"courses_audit":0,"courses_uuid":"122"},{"courses_dept":"fren\r","courses_id":"58801","courses_avg":78,"courses_instructor":"","courses_title":"fren lang&lit i","courses_pass":25,"courses_fail":0,"courses_audit":0,"courses_uuid":"122"},{"courses_dept":"fren\r","courses_id":"58802","courses_avg":75.11,"courses_instructor":"","courses_title":"fren lang&lit i","courses_pass":206,"courses_fail":3,"courses_audit":2,"courses_uuid":"122"},{"courses_dept":"fren\r","courses_id":"58913","courses_avg":73.95,"courses_instructor":"o'hagan, michael","courses_title":"fren lang&lit i","courses_pass":19,"courses_fail":1,"courses_audit":0,"courses_uuid":"122"},{"courses_dept":"fren\r","courses_id":"58914","courses_avg":73.89,"courses_instructor":"miller, robert","courses_title":"fren lang&lit i","courses_pass":26,"courses_fail":2,"courses_audit":0,"courses_uuid":"122"},{"courses_dept":"fren\r","courses_id":"58915","courses_avg":64.41,"courses_instructor":"bodolec, jacques","courses_title":"fren lang&lit i","courses_pass":18,"courses_fail":4,"courses_audit":0,"courses_uuid":"122"},{"courses_dept":"fren\r","courses_id":"58916","courses_avg":63.74,"courses_instructor":"o'hagan, michael","courses_title":"fren lang&lit i","courses_pass":15,"courses_fail":4,"courses_audit":0,"courses_uuid":"122"},{"courses_dept":"fren\r","courses_id":"58917","courses_avg":73.79,"courses_instructor":"scott, anne","courses_title":"fren lang&lit i","courses_pass":29,"courses_fail":0,"courses_audit":0,"courses_uuid":"122"},{"courses_dept":"fren\r","courses_id":"58918","courses_avg":75.48,"courses_instructor":"o'brien, juliet","courses_title":"fren lang&lit i","courses_pass":26,"courses_fail":1,"courses_audit":0,"courses_uuid":"122"},{"courses_dept":"fren\r","courses_id":"58919","courses_avg":70.19,"courses_instructor":"huberman, ben","courses_title":"fren lang&lit i","courses_pass":24,"courses_fail":2,"courses_audit":0,"courses_uuid":"122"},{"courses_dept":"fren\r","courses_id":"58920","courses_avg":74.79,"courses_instructor":"simpson, anne","courses_title":"fren lang&lit i","courses_pass":23,"courses_fail":1,"courses_audit":0,"courses_uuid":"122"},{"courses_dept":"fren\r","courses_id":"58921","courses_avg":72.93,"courses_instructor":"culbert, john","courses_title":"fren lang&lit i","courses_pass":29,"courses_fail":1,"courses_audit":0,"courses_uuid":"122"},{"courses_dept":"fren\r","courses_id":"58922","courses_avg":75.22,"courses_instructor":"godfrey, sima","courses_title":"fren lang&lit i","courses_pass":18,"courses_fail":0,"courses_audit":0,"courses_uuid":"122"},{"courses_dept":"fren\r","courses_id":"58923","courses_avg":65.71,"courses_instructor":"phan, chantal","courses_title":"fren lang&lit i","courses_pass":15,"courses_fail":2,"courses_audit":0,"courses_uuid":"122"},{"courses_dept":"fren\r","courses_id":"58924","courses_avg":71.67,"courses_instructor":"","courses_title":"fren lang&lit i","courses_pass":242,"courses_fail":18,"courses_audit":0,"courses_uuid":"122"},{"courses_dept":"fren\r","courses_id":"77657","courses_avg":77,"courses_instructor":"palisse, stephanie","courses_title":"fren lang&lit i","courses_pass":26,"courses_fail":0,"courses_audit":0,"courses_uuid":"122"},{"courses_dept":"fren\r","courses_id":"77658","courses_avg":69.61,"courses_instructor":"onyeoziri-miller, gloria","courses_title":"fren lang&lit i","courses_pass":21,"courses_fail":2,"courses_audit":0,"courses_uuid":"122"},{"courses_dept":"fren\r","courses_id":"77659","courses_avg":77.53,"courses_instructor":"scott, anne","courses_title":"fren lang&lit i","courses_pass":30,"courses_fail":0,"courses_audit":0,"courses_uuid":"122"},{"courses_dept":"fren\r","courses_id":"77660","courses_avg":77.11,"courses_instructor":"miller, robert","courses_title":"fren lang&lit i","courses_pass":27,"courses_fail":0,"courses_audit":0,"courses_uuid":"122"},{"courses_dept":"fren\r","courses_id":"77661","courses_avg":71.85,"courses_instructor":"winder, william","courses_title":"fren lang&lit i","courses_pass":26,"courses_fail":1,"courses_audit":0,"courses_uuid":"122"},{"courses_dept":"fren\r","courses_id":"77662","courses_avg":75.63,"courses_instructor":"phan, chantal","courses_title":"fren lang&lit i","courses_pass":15,"courses_fail":1,"courses_audit":1,"courses_uuid":"122"},{"courses_dept":"fren\r","courses_id":"77663","courses_avg":78.46,"courses_instructor":"scott, anne","courses_title":"fren lang&lit i","courses_pass":24,"courses_fail":0,"courses_audit":0,"courses_uuid":"122"},{"courses_dept":"fren\r","courses_id":"77664","courses_avg":79.3,"courses_instructor":"laroussi, farid","courses_title":"fren lang&lit i","courses_pass":23,"courses_fail":0,"courses_audit":0,"courses_uuid":"122"},{"courses_dept":"fren\r","courses_id":"77665","courses_avg":72.88,"courses_instructor":"hodgson, richard","courses_title":"fren lang&lit i","courses_pass":21,"courses_fail":3,"courses_audit":0,"courses_uuid":"122"},{"courses_dept":"fren\r","courses_id":"77666","courses_avg":75.53,"courses_instructor":"","courses_title":"fren lang&lit i","courses_pass":213,"courses_fail":7,"courses_audit":1,"courses_uuid":"122"},{"courses_dept":"fren\r","courses_id":"81390","courses_avg":77.5,"courses_instructor":"winder, william","courses_title":"fren lang&lit i","courses_pass":20,"courses_fail":0,"courses_audit":0,"courses_uuid":"122"},{"courses_dept":"fren\r","courses_id":"81391","courses_avg":77.5,"courses_instructor":"","courses_title":"fren lang&lit i","courses_pass":20,"courses_fail":0,"courses_audit":0,"courses_uuid":"122"},{"courses_dept":"fren\r","courses_id":"84430","courses_avg":73.93,"courses_instructor":"winder, william","courses_title":"fren lang&lit i","courses_pass":27,"courses_fail":0,"courses_audit":0,"courses_uuid":"122"},{"courses_dept":"fren\r","courses_id":"84431","courses_avg":73.93,"courses_instructor":"","courses_title":"fren lang&lit i","courses_pass":27,"courses_fail":0,"courses_audit":0,"courses_uuid":"122"},{"courses_dept":"fren\r","courses_id":"87193","courses_avg":72.47,"courses_instructor":"bascou vallarino, sylvia","courses_title":"fren lang&lit i","courses_pass":16,"courses_fail":1,"courses_audit":4,"courses_uuid":"122"},{"courses_dept":"fren\r","courses_id":"87194","courses_avg":72.47,"courses_instructor":"","courses_title":"fren lang&lit i","courses_pass":16,"courses_fail":1,"courses_audit":4,"courses_uuid":"122"},{"courses_dept":"fren\r","courses_id":"90706","courses_avg":70.32,"courses_instructor":"bodolec, jacques","courses_title":"fren lang&lit i","courses_pass":22,"courses_fail":3,"courses_audit":0,"courses_uuid":"122"},{"courses_dept":"fren\r","courses_id":"90707","courses_avg":70.29,"courses_instructor":"jean, marie-gerald;miller, robert;scott, anne","courses_title":"fren lang&lit i","courses_pass":23,"courses_fail":1,"courses_audit":0,"courses_uuid":"122"},{"courses_dept":"fren\r","courses_id":"90708","courses_avg":73.73,"courses_instructor":"rocheleau, alain-michel","courses_title":"fren lang&lit i","courses_pass":25,"courses_fail":1,"courses_audit":0,"courses_uuid":"122"},{"courses_dept":"fren\r","courses_id":"90709","courses_avg":72.03,"courses_instructor":"rocheleau, alain-michel","courses_title":"fren lang&lit i","courses_pass":28,"courses_fail":2,"courses_audit":0,"courses_uuid":"122"},{"courses_dept":"fren\r","courses_id":"90710","courses_avg":72.1,"courses_instructor":"scott, anne","courses_title":"fren lang&lit i","courses_pass":29,"courses_fail":1,"courses_audit":0,"courses_uuid":"122"},{"courses_dept":"fren\r","courses_id":"90711","courses_avg":76.19,"courses_instructor":"miller, robert","courses_title":"fren lang&lit i","courses_pass":21,"courses_fail":0,"courses_audit":0,"courses_uuid":"122"},{"courses_dept":"fren\r","courses_id":"90712","courses_avg":71.82,"courses_instructor":"onyeoziri-miller, gloria","courses_title":"fren lang&lit i","courses_pass":22,"courses_fail":0,"courses_audit":0,"courses_uuid":"122"},{"courses_dept":"fren\r","courses_id":"90713","courses_avg":70.38,"courses_instructor":"tran thanh, julia","courses_title":"fren lang&lit i","courses_pass":24,"courses_fail":0,"courses_audit":0,"courses_uuid":"122"},{"courses_dept":"fren\r","courses_id":"90714","courses_avg":70,"courses_instructor":"winder, william","courses_title":"fren lang&lit i","courses_pass":22,"courses_fail":3,"courses_audit":0,"courses_uuid":"122"},{"courses_dept":"fren\r","courses_id":"90715","courses_avg":76.41,"courses_instructor":"miller, robert;scott, anne;shilliday, molleen","courses_title":"fren lang&lit i","courses_pass":21,"courses_fail":1,"courses_audit":1,"courses_uuid":"122"},{"courses_dept":"fren\r","courses_id":"90716","courses_avg":77.36,"courses_instructor":"o'brien, juliet","courses_title":"fren lang&lit i","courses_pass":22,"courses_fail":0,"courses_audit":0,"courses_uuid":"122"},{"courses_dept":"fren\r","courses_id":"90717","courses_avg":72.65,"courses_instructor":"","courses_title":"fren lang&lit i","courses_pass":259,"courses_fail":12,"courses_audit":1,"courses_uuid":"122"},{"courses_dept":"fren\r","courses_id":"94305","courses_avg":72.64,"courses_instructor":"miller, robert","courses_title":"fren lang&lit i","courses_pass":24,"courses_fail":1,"courses_audit":0,"courses_uuid":"122"},{"courses_dept":"fren\r","courses_id":"94306","courses_avg":75.27,"courses_instructor":"winder, william","courses_title":"fren lang&lit i","courses_pass":22,"courses_fail":0,"courses_audit":0,"courses_uuid":"122"},{"courses_dept":"fren\r","courses_id":"94307","courses_avg":76.33,"courses_instructor":"miller, robert;scott, anne;shilliday, molleen","courses_title":"fren lang&lit i","courses_pass":27,"courses_fail":0,"courses_audit":0,"courses_uuid":"122"},{"courses_dept":"fren\r","courses_id":"94308","courses_avg":75.48,"courses_instructor":"caute, adeline;miller, robert;scott, anne","courses_title":"fren lang&lit i","courses_pass":27,"courses_fail":0,"courses_audit":0,"courses_uuid":"122"},{"courses_dept":"fren\r","courses_id":"94309","courses_avg":77.26,"courses_instructor":"godfrey, sima","courses_title":"fren lang&lit i","courses_pass":23,"courses_fail":0,"courses_audit":0,"courses_uuid":"122"},{"courses_dept":"fren\r","courses_id":"94310","courses_avg":75,"courses_instructor":"miller, robert","courses_title":"fren lang&lit i","courses_pass":26,"courses_fail":1,"courses_audit":0,"courses_uuid":"122"},{"courses_dept":"fren\r","courses_id":"94311","courses_avg":75.2,"courses_instructor":"winder, william","courses_title":"fren lang&lit i","courses_pass":19,"courses_fail":1,"courses_audit":0,"courses_uuid":"122"},{"courses_dept":"fren\r","courses_id":"94312","courses_avg":71.54,"courses_instructor":"scott, anne","courses_title":"fren lang&lit i","courses_pass":26,"courses_fail":0,"courses_audit":0,"courses_uuid":"122"},{"courses_dept":"fren\r","courses_id":"94313","courses_avg":75.78,"courses_instructor":"bascou vallarino, sylvia","courses_title":"fren lang&lit i","courses_pass":23,"courses_fail":0,"courses_audit":0,"courses_uuid":"122"},{"courses_dept":"fren\r","courses_id":"94314","courses_avg":72.4,"courses_instructor":"berard, stephanie","courses_title":"fren lang&lit i","courses_pass":24,"courses_fail":1,"courses_audit":0,"courses_uuid":"122"},{"courses_dept":"fren\r","courses_id":"94315","courses_avg":76.37,"courses_instructor":"o'brien, juliet","courses_title":"fren lang&lit i","courses_pass":27,"courses_fail":0,"courses_audit":0,"courses_uuid":"122"},{"courses_dept":"fren\r","courses_id":"94316","courses_avg":77.68,"courses_instructor":"simpson, anne","courses_title":"fren lang&lit i","courses_pass":25,"courses_fail":0,"courses_audit":0,"courses_uuid":"122"},{"courses_dept":"fren\r","courses_id":"94317","courses_avg":75.06,"courses_instructor":"","courses_title":"fren lang&lit i","courses_pass":293,"courses_fail":4,"courses_audit":0,"courses_uuid":"122"}]}