{"table":[{"courses_dept":"hist\r","courses_id":"14382","courses_avg":73.25,"courses_instructor":"lanthier, michael","courses_title":"early 20c brit","courses_pass":36,"courses_fail":0,"courses_audit":0,"courses_uuid":"318"},{"courses_dept":"hist\r","courses_id":"14383","courses_avg":73.25,"courses_instructor":"","courses_title":"early 20c brit","courses_pass":36,"courses_fail":0,"courses_audit":0,"courses_uuid":"318"},{"courses_dept":"hist\r","courses_id":"29521","courses_avg":71.29,"courses_instructor":"dixon, joy","courses_title":"early 20c brit","courses_pass":42,"courses_fail":3,"courses_audit":0,"courses_uuid":"318"},{"courses_dept":"hist\r","courses_id":"29522","courses_avg":71.29,"courses_instructor":"","courses_title":"early 20c brit","courses_pass":42,"courses_fail":3,"courses_audit":0,"courses_uuid":"318"},{"courses_dept":"hist\r","courses_id":"38312","courses_avg":72.11,"courses_instructor":"dixon, joy","courses_title":"early 20c brit","courses_pass":59,"courses_fail":2,"courses_audit":0,"courses_uuid":"318"},{"courses_dept":"hist\r","courses_id":"38313","courses_avg":72.11,"courses_instructor":"","courses_title":"early 20c brit","courses_pass":59,"courses_fail":2,"courses_audit":0,"courses_uuid":"318"},{"courses_dept":"hist\r","courses_id":"61724","courses_avg":70.84,"courses_instructor":"dixon, joy","courses_title":"early 20c brit","courses_pass":55,"courses_fail":3,"courses_audit":0,"courses_uuid":"318"},{"courses_dept":"hist\r","courses_id":"61725","courses_avg":70.84,"courses_instructor":"","courses_title":"early 20c brit","courses_pass":55,"courses_fail":3,"courses_audit":0,"courses_uuid":"318"},{"courses_dept":"hist\r","courses_id":"66669","courses_avg":71.55,"courses_instructor":"dixon, joy","courses_title":"early 20c brit","courses_pass":35,"courses_fail":5,"courses_audit":0,"courses_uuid":"318"},{"courses_dept":"hist\r","courses_id":"66670","courses_avg":71.55,"courses_instructor":"","courses_title":"early 20c brit","courses_pass":35,"courses_fail":5,"courses_audit":0,"courses_uuid":"318"},{"courses_dept":"hist\r","courses_id":"79734","courses_avg":71.92,"courses_instructor":"","courses_title":"early 20c brit","courses_pass":12,"courses_fail":0,"courses_audit":0,"courses_uuid":"318"},{"courses_dept":"hist\r","courses_id":"79735","courses_avg":71.92,"courses_instructor":"","courses_title":"early 20c brit","courses_pass":12,"courses_fail":0,"courses_audit":0,"courses_uuid":"318"},{"courses_dept":"hist\r","courses_id":"85427","courses_avg":72.89,"courses_instructor":"bil, geoffrey","courses_title":"early 20c brit","courses_pass":38,"courses_fail":0,"courses_audit":0,"courses_uuid":"318"},{"courses_dept":"hist\r","courses_id":"85428","courses_avg":72.89,"courses_instructor":"","courses_title":"early 20c brit","courses_pass":38,"courses_fail":0,"courses_audit":0,"courses_uuid":"318"}]}