{"table":[{"courses_dept":"libr","courses_id":"15888","courses_avg":83,"courses_instructor":"loehrlein, aaron","courses_title":"resdesc knoworg","courses_pass":46,"courses_fail":0,"courses_audit":0,"courses_uuid":"509"},{"courses_dept":"libr","courses_id":"15889","courses_avg":83,"courses_instructor":"","courses_title":"resdesc knoworg","courses_pass":46,"courses_fail":0,"courses_audit":0,"courses_uuid":"509"},{"courses_dept":"libr","courses_id":"77237","courses_avg":83,"courses_instructor":"loehrlein, aaron","courses_title":"resdesc knoworg","courses_pass":42,"courses_fail":0,"courses_audit":0,"courses_uuid":"509"},{"courses_dept":"libr","courses_id":"77238","courses_avg":83,"courses_instructor":"loehrlein, aaron","courses_title":"resdesc knoworg","courses_pass":33,"courses_fail":0,"courses_audit":0,"courses_uuid":"509"},{"courses_dept":"libr","courses_id":"77239","courses_avg":83,"courses_instructor":"","courses_title":"resdesc knoworg","courses_pass":75,"courses_fail":0,"courses_audit":0,"courses_uuid":"509"}]}