{"table":[{"courses_dept":"musc","courses_id":"454","courses_avg":76.1,"courses_instructor":"law, sin yan hedy","courses_title":"hist of opera i","courses_pass":21,"courses_fail":0,"courses_audit":0,"courses_uuid":"7246"},{"courses_dept":"musc","courses_id":"454","courses_avg":76.1,"courses_instructor":"","courses_title":"hist of opera i","courses_pass":21,"courses_fail":0,"courses_audit":0,"courses_uuid":"7247"},{"courses_dept":"musc","courses_id":"454","courses_avg":73.59,"courses_instructor":"law, sin yan hedy","courses_title":"hist of opera i","courses_pass":27,"courses_fail":0,"courses_audit":0,"courses_uuid":"28827"},{"courses_dept":"musc","courses_id":"454","courses_avg":73.59,"courses_instructor":"","courses_title":"hist of opera i","courses_pass":27,"courses_fail":0,"courses_audit":0,"courses_uuid":"28828"},{"courses_dept":"musc","courses_id":"454","courses_avg":60.04,"courses_instructor":"butler, gregory g","courses_title":"hist of opera i","courses_pass":21,"courses_fail":4,"courses_audit":7,"courses_uuid":"41002"},{"courses_dept":"musc","courses_id":"454","courses_avg":60.04,"courses_instructor":"","courses_title":"hist of opera i","courses_pass":21,"courses_fail":4,"courses_audit":7,"courses_uuid":"41003"},{"courses_dept":"musc","courses_id":"454","courses_avg":63.52,"courses_instructor":"butler, gregory g","courses_title":"hist of opera i","courses_pass":29,"courses_fail":2,"courses_audit":1,"courses_uuid":"66007"},{"courses_dept":"musc","courses_id":"454","courses_avg":63.52,"courses_instructor":"","courses_title":"hist of opera i","courses_pass":29,"courses_fail":2,"courses_audit":1,"courses_uuid":"66008"},{"courses_dept":"musc","courses_id":"454","courses_avg":73.2,"courses_instructor":"butler, gregory g","courses_title":"hist of opera i","courses_pass":30,"courses_fail":0,"courses_audit":0,"courses_uuid":"93915"},{"courses_dept":"musc","courses_id":"454","courses_avg":73.2,"courses_instructor":"","courses_title":"hist of opera i","courses_pass":30,"courses_fail":0,"courses_audit":0,"courses_uuid":"93916"}]}