{"table":[{"courses_dept":"nurs","courses_id":"15345","courses_avg":94,"courses_instructor":"mccuaig, fairleth","courses_title":"adv hlth assess","courses_pass":14,"courses_fail":0,"courses_audit":0,"courses_uuid":"510"},{"courses_dept":"nurs","courses_id":"15346","courses_avg":94,"courses_instructor":"","courses_title":"adv hlth assess","courses_pass":14,"courses_fail":0,"courses_audit":0,"courses_uuid":"510"},{"courses_dept":"nurs","courses_id":"35345","courses_avg":91,"courses_instructor":"jennings,  mary lou;mccuaig, fairleth","courses_title":"adv hlth assess","courses_pass":14,"courses_fail":0,"courses_audit":0,"courses_uuid":"510"},{"courses_dept":"nurs","courses_id":"35346","courses_avg":91,"courses_instructor":"","courses_title":"adv hlth assess","courses_pass":14,"courses_fail":0,"courses_audit":0,"courses_uuid":"510"},{"courses_dept":"nurs","courses_id":"40693","courses_avg":89,"courses_instructor":"","courses_title":"adv hlth assess","courses_pass":14,"courses_fail":0,"courses_audit":0,"courses_uuid":"510"},{"courses_dept":"nurs","courses_id":"40694","courses_avg":89,"courses_instructor":"","courses_title":"adv hlth assess","courses_pass":14,"courses_fail":0,"courses_audit":0,"courses_uuid":"510"},{"courses_dept":"nurs","courses_id":"47395","courses_avg":90,"courses_instructor":"mccuaig, fairleth","courses_title":"adv hlth assess","courses_pass":16,"courses_fail":0,"courses_audit":0,"courses_uuid":"510"},{"courses_dept":"nurs","courses_id":"47396","courses_avg":90,"courses_instructor":"","courses_title":"adv hlth assess","courses_pass":16,"courses_fail":0,"courses_audit":0,"courses_uuid":"510"},{"courses_dept":"nurs","courses_id":"73640","courses_avg":94,"courses_instructor":"burrows, marlene;harding, jillian;mccuaig, fairleth","courses_title":"adv hlth assess","courses_pass":15,"courses_fail":0,"courses_audit":0,"courses_uuid":"510"},{"courses_dept":"nurs","courses_id":"73641","courses_avg":94,"courses_instructor":"","courses_title":"adv hlth assess","courses_pass":15,"courses_fail":0,"courses_audit":0,"courses_uuid":"510"},{"courses_dept":"nurs","courses_id":"78719","courses_avg":91,"courses_instructor":"harding, jillian;krist, jennifer;mccuaig, fairleth","courses_title":"adv hlth assess","courses_pass":15,"courses_fail":0,"courses_audit":0,"courses_uuid":"510"},{"courses_dept":"nurs","courses_id":"78720","courses_avg":91,"courses_instructor":"","courses_title":"adv hlth assess","courses_pass":15,"courses_fail":0,"courses_audit":0,"courses_uuid":"510"},{"courses_dept":"nurs","courses_id":"88119","courses_avg":91,"courses_instructor":"harding, jillian;krist, jennifer;mccuaig, fairleth","courses_title":"adv hlth assess","courses_pass":15,"courses_fail":0,"courses_audit":0,"courses_uuid":"510"},{"courses_dept":"nurs","courses_id":"88120","courses_avg":91,"courses_instructor":"","courses_title":"adv hlth assess","courses_pass":15,"courses_fail":0,"courses_audit":0,"courses_uuid":"510"},{"courses_dept":"nurs","courses_id":"93107","courses_avg":93,"courses_instructor":"burrows, marlene;mccuaig, fairleth","courses_title":"adv hlth assess","courses_pass":15,"courses_fail":0,"courses_audit":0,"courses_uuid":"510"},{"courses_dept":"nurs","courses_id":"93108","courses_avg":93,"courses_instructor":"","courses_title":"adv hlth assess","courses_pass":15,"courses_fail":0,"courses_audit":0,"courses_uuid":"510"},{"courses_dept":"nurs","courses_id":"96216","courses_avg":90,"courses_instructor":"brown, helen jean;mccuaig, fairleth","courses_title":"adv hlth assess","courses_pass":14,"courses_fail":0,"courses_audit":0,"courses_uuid":"510"},{"courses_dept":"nurs","courses_id":"96217","courses_avg":90,"courses_instructor":"","courses_title":"adv hlth assess","courses_pass":14,"courses_fail":0,"courses_audit":0,"courses_uuid":"510"}]}