{"table":[{"courses_dept":"phil","courses_id":"125","courses_avg":77.63,"courses_instructor":"burkholder, leslie","courses_title":"scientifc reason","courses_pass":24,"courses_fail":0,"courses_audit":0,"courses_uuid":"8392"},{"courses_dept":"phil","courses_id":"125","courses_avg":67.42,"courses_instructor":"burkholder, leslie","courses_title":"scientifc reason","courses_pass":59,"courses_fail":10,"courses_audit":0,"courses_uuid":"8393"},{"courses_dept":"phil","courses_id":"125","courses_avg":73.53,"courses_instructor":"korolev, alexandre","courses_title":"scientifc reason","courses_pass":34,"courses_fail":0,"courses_audit":0,"courses_uuid":"8394"},{"courses_dept":"phil","courses_id":"125","courses_avg":70.98,"courses_instructor":"","courses_title":"scientifc reason","courses_pass":117,"courses_fail":10,"courses_audit":0,"courses_uuid":"8395"},{"courses_dept":"phil","courses_id":"125","courses_avg":73.08,"courses_instructor":"burkholder, leslie","courses_title":"scientifc reason","courses_pass":35,"courses_fail":3,"courses_audit":1,"courses_uuid":"20193"},{"courses_dept":"phil","courses_id":"125","courses_avg":73.08,"courses_instructor":"","courses_title":"scientifc reason","courses_pass":35,"courses_fail":3,"courses_audit":1,"courses_uuid":"20194"},{"courses_dept":"phil","courses_id":"125","courses_avg":66.5,"courses_instructor":"johns, richard","courses_title":"scientifc reason","courses_pass":31,"courses_fail":3,"courses_audit":0,"courses_uuid":"20368"},{"courses_dept":"phil","courses_id":"125","courses_avg":70.07,"courses_instructor":"stanev, roger","courses_title":"scientifc reason","courses_pass":25,"courses_fail":2,"courses_audit":0,"courses_uuid":"20369"},{"courses_dept":"phil","courses_id":"125","courses_avg":73.33,"courses_instructor":"burkholder, leslie","courses_title":"scientifc reason","courses_pass":63,"courses_fail":4,"courses_audit":0,"courses_uuid":"20370"},{"courses_dept":"phil","courses_id":"125","courses_avg":70.83,"courses_instructor":"","courses_title":"scientifc reason","courses_pass":119,"courses_fail":9,"courses_audit":0,"courses_uuid":"20371"},{"courses_dept":"phil","courses_id":"125","courses_avg":72.47,"courses_instructor":"burkholder, leslie","courses_title":"scientifc reason","courses_pass":30,"courses_fail":0,"courses_audit":1,"courses_uuid":"24649"},{"courses_dept":"phil","courses_id":"125","courses_avg":72.47,"courses_instructor":"","courses_title":"scientifc reason","courses_pass":30,"courses_fail":0,"courses_audit":1,"courses_uuid":"24650"},{"courses_dept":"phil","courses_id":"125","courses_avg":68.53,"courses_instructor":"stanev, roger","courses_title":"scientifc reason","courses_pass":19,"courses_fail":0,"courses_audit":0,"courses_uuid":"24880"},{"courses_dept":"phil","courses_id":"125","courses_avg":68.53,"courses_instructor":"","courses_title":"scientifc reason","courses_pass":19,"courses_fail":0,"courses_audit":0,"courses_uuid":"24881"},{"courses_dept":"phil","courses_id":"125","courses_avg":75.13,"courses_instructor":"burkholder, leslie","courses_title":"scientifc reason","courses_pass":23,"courses_fail":1,"courses_audit":0,"courses_uuid":"24992"},{"courses_dept":"phil","courses_id":"125","courses_avg":69.52,"courses_instructor":"burkholder, leslie","courses_title":"scientifc reason","courses_pass":40,"courses_fail":4,"courses_audit":0,"courses_uuid":"24993"},{"courses_dept":"phil","courses_id":"125","courses_avg":70.21,"courses_instructor":"hepburn, brian","courses_title":"scientifc reason","courses_pass":25,"courses_fail":3,"courses_audit":0,"courses_uuid":"24994"},{"courses_dept":"phil","courses_id":"125","courses_avg":71.13,"courses_instructor":"","courses_title":"scientifc reason","courses_pass":88,"courses_fail":8,"courses_audit":0,"courses_uuid":"24995"},{"courses_dept":"phil","courses_id":"125","courses_avg":68.06,"courses_instructor":"burkholder, leslie","courses_title":"scientifc reason","courses_pass":152,"courses_fail":15,"courses_audit":1,"courses_uuid":"33184"},{"courses_dept":"phil","courses_id":"125","courses_avg":66.19,"courses_instructor":"burkholder, leslie","courses_title":"scientifc reason","courses_pass":165,"courses_fail":23,"courses_audit":0,"courses_uuid":"33185"},{"courses_dept":"phil","courses_id":"125","courses_avg":67.07,"courses_instructor":"","courses_title":"scientifc reason","courses_pass":317,"courses_fail":38,"courses_audit":1,"courses_uuid":"33186"},{"courses_dept":"phil","courses_id":"125","courses_avg":73.79,"courses_instructor":"","courses_title":"scientifc reason","courses_pass":31,"courses_fail":2,"courses_audit":0,"courses_uuid":"37832"},{"courses_dept":"phil","courses_id":"125","courses_avg":74.69,"courses_instructor":"","courses_title":"scientifc reason","courses_pass":31,"courses_fail":1,"courses_audit":0,"courses_uuid":"37833"},{"courses_dept":"phil","courses_id":"125","courses_avg":68.34,"courses_instructor":"","courses_title":"scientifc reason","courses_pass":122,"courses_fail":15,"courses_audit":0,"courses_uuid":"37834"},{"courses_dept":"phil","courses_id":"125","courses_avg":70.24,"courses_instructor":"","courses_title":"scientifc reason","courses_pass":184,"courses_fail":18,"courses_audit":0,"courses_uuid":"37835"},{"courses_dept":"phil","courses_id":"125","courses_avg":74.44,"courses_instructor":"amitani, yuichi","courses_title":"scientifc reason","courses_pass":34,"courses_fail":2,"courses_audit":0,"courses_uuid":"43214"},{"courses_dept":"phil","courses_id":"125","courses_avg":74.44,"courses_instructor":"","courses_title":"scientifc reason","courses_pass":34,"courses_fail":2,"courses_audit":0,"courses_uuid":"43215"},{"courses_dept":"phil","courses_id":"125","courses_avg":70.28,"courses_instructor":"burkholder, leslie","courses_title":"scientifc reason","courses_pass":55,"courses_fail":3,"courses_audit":0,"courses_uuid":"43708"},{"courses_dept":"phil","courses_id":"125","courses_avg":66.17,"courses_instructor":"burkholder, leslie","courses_title":"scientifc reason","courses_pass":38,"courses_fail":3,"courses_audit":0,"courses_uuid":"43709"},{"courses_dept":"phil","courses_id":"125","courses_avg":68.58,"courses_instructor":"","courses_title":"scientifc reason","courses_pass":93,"courses_fail":6,"courses_audit":0,"courses_uuid":"43710"},{"courses_dept":"phil","courses_id":"125","courses_avg":68.39,"courses_instructor":"burkholder, leslie","courses_title":"scientifc reason","courses_pass":65,"courses_fail":10,"courses_audit":1,"courses_uuid":"49170"},{"courses_dept":"phil","courses_id":"125","courses_avg":68.04,"courses_instructor":"burkholder, leslie","courses_title":"scientifc reason","courses_pass":63,"courses_fail":8,"courses_audit":0,"courses_uuid":"49171"},{"courses_dept":"phil","courses_id":"125","courses_avg":68.22,"courses_instructor":"","courses_title":"scientifc reason","courses_pass":128,"courses_fail":18,"courses_audit":1,"courses_uuid":"49172"},{"courses_dept":"phil","courses_id":"125","courses_avg":79.14,"courses_instructor":"","courses_title":"scientifc reason","courses_pass":40,"courses_fail":3,"courses_audit":0,"courses_uuid":"51677"},{"courses_dept":"phil","courses_id":"125","courses_avg":79.14,"courses_instructor":"","courses_title":"scientifc reason","courses_pass":40,"courses_fail":3,"courses_audit":0,"courses_uuid":"51678"},{"courses_dept":"phil","courses_id":"125","courses_avg":71.34,"courses_instructor":"burkholder, leslie","courses_title":"scientifc reason","courses_pass":57,"courses_fail":4,"courses_audit":1,"courses_uuid":"58654"},{"courses_dept":"phil","courses_id":"125","courses_avg":68.74,"courses_instructor":"burkholder, leslie","courses_title":"scientifc reason","courses_pass":59,"courses_fail":11,"courses_audit":0,"courses_uuid":"58655"},{"courses_dept":"phil","courses_id":"125","courses_avg":69.95,"courses_instructor":"","courses_title":"scientifc reason","courses_pass":116,"courses_fail":15,"courses_audit":1,"courses_uuid":"58656"},{"courses_dept":"phil","courses_id":"125","courses_avg":78.1,"courses_instructor":"french, christopher","courses_title":"scientifc reason","courses_pass":10,"courses_fail":0,"courses_audit":0,"courses_uuid":"62083"},{"courses_dept":"phil","courses_id":"125","courses_avg":78.1,"courses_instructor":"","courses_title":"scientifc reason","courses_pass":10,"courses_fail":0,"courses_audit":0,"courses_uuid":"62084"},{"courses_dept":"phil","courses_id":"125","courses_avg":70.63,"courses_instructor":"french, christopher","courses_title":"scientifc reason","courses_pass":25,"courses_fail":2,"courses_audit":0,"courses_uuid":"70262"},{"courses_dept":"phil","courses_id":"125","courses_avg":81.56,"courses_instructor":"burkholder, leslie","courses_title":"scientifc reason","courses_pass":115,"courses_fail":6,"courses_audit":0,"courses_uuid":"70263"},{"courses_dept":"phil","courses_id":"125","courses_avg":79.57,"courses_instructor":"","courses_title":"scientifc reason","courses_pass":140,"courses_fail":8,"courses_audit":0,"courses_uuid":"70264"}]}