{"table":[{"courses_dept":"phys","courses_id":"437","courses_avg":78,"courses_instructor":"kotlicki, andrzej","courses_title":"intmd exp phys 2","courses_pass":33,"courses_fail":2,"courses_audit":0,"courses_uuid":"229"},{"courses_dept":"phys","courses_id":"438","courses_avg":88,"courses_instructor":"milner, valery","courses_title":"intmd exp phys 2","courses_pass":37,"courses_fail":0,"courses_audit":0,"courses_uuid":"229"},{"courses_dept":"phys","courses_id":"439","courses_avg":81,"courses_instructor":"milner, valery","courses_title":"intmd exp phys 2","courses_pass":35,"courses_fail":1,"courses_audit":0,"courses_uuid":"229"},{"courses_dept":"phys","courses_id":"440","courses_avg":82,"courses_instructor":"","courses_title":"intmd exp phys 2","courses_pass":105,"courses_fail":3,"courses_audit":0,"courses_uuid":"229"},{"courses_dept":"phys","courses_id":"98730","courses_avg":82,"courses_instructor":"kotlicki, andrzej","courses_title":"intmd exp phys 2","courses_pass":22,"courses_fail":0,"courses_audit":0,"courses_uuid":"229"},{"courses_dept":"phys","courses_id":"98731","courses_avg":83,"courses_instructor":"milner, valery","courses_title":"intmd exp phys 2","courses_pass":29,"courses_fail":0,"courses_audit":0,"courses_uuid":"229"},{"courses_dept":"phys","courses_id":"98732","courses_avg":84,"courses_instructor":"milner, valery","courses_title":"intmd exp phys 2","courses_pass":24,"courses_fail":0,"courses_audit":0,"courses_uuid":"229"},{"courses_dept":"phys","courses_id":"98733","courses_avg":83,"courses_instructor":"","courses_title":"intmd exp phys 2","courses_pass":75,"courses_fail":0,"courses_audit":0,"courses_uuid":"229"}]}