{"table":[{"courses_dept":"pols","courses_id":"8361","courses_avg":81,"courses_instructor":"karwowska, bozena","courses_title":"lit&film translt","courses_pass":31,"courses_fail":0,"courses_audit":1,"courses_uuid":"424"},{"courses_dept":"pols","courses_id":"8362","courses_avg":81,"courses_instructor":"","courses_title":"lit&film translt","courses_pass":31,"courses_fail":0,"courses_audit":1,"courses_uuid":"424"},{"courses_dept":"pols","courses_id":"11905","courses_avg":81,"courses_instructor":"karwowska, bozena","courses_title":"lit&film translt","courses_pass":22,"courses_fail":0,"courses_audit":0,"courses_uuid":"424"},{"courses_dept":"pols","courses_id":"11906","courses_avg":81,"courses_instructor":"","courses_title":"lit&film translt","courses_pass":22,"courses_fail":0,"courses_audit":0,"courses_uuid":"424"},{"courses_dept":"pols","courses_id":"18775","courses_avg":77,"courses_instructor":"karwowska, bozena","courses_title":"lit&film translt","courses_pass":36,"courses_fail":0,"courses_audit":0,"courses_uuid":"424"},{"courses_dept":"pols","courses_id":"18776","courses_avg":77,"courses_instructor":"","courses_title":"lit&film translt","courses_pass":36,"courses_fail":0,"courses_audit":0,"courses_uuid":"424"},{"courses_dept":"pols","courses_id":"23421","courses_avg":79,"courses_instructor":"karwowska, bozena","courses_title":"lit&film translt","courses_pass":21,"courses_fail":0,"courses_audit":0,"courses_uuid":"424"},{"courses_dept":"pols","courses_id":"23422","courses_avg":79,"courses_instructor":"","courses_title":"lit&film translt","courses_pass":21,"courses_fail":0,"courses_audit":0,"courses_uuid":"424"},{"courses_dept":"pols","courses_id":"40304","courses_avg":83,"courses_instructor":"","courses_title":"lit&film translt","courses_pass":31,"courses_fail":0,"courses_audit":0,"courses_uuid":"424"},{"courses_dept":"pols","courses_id":"40305","courses_avg":83,"courses_instructor":"","courses_title":"lit&film translt","courses_pass":31,"courses_fail":0,"courses_audit":0,"courses_uuid":"424"},{"courses_dept":"pols","courses_id":"51431","courses_avg":80,"courses_instructor":"karwowska, bozena","courses_title":"lit&film translt","courses_pass":16,"courses_fail":0,"courses_audit":0,"courses_uuid":"424"},{"courses_dept":"pols","courses_id":"51432","courses_avg":80,"courses_instructor":"","courses_title":"lit&film translt","courses_pass":16,"courses_fail":0,"courses_audit":0,"courses_uuid":"424"},{"courses_dept":"pols","courses_id":"57710","courses_avg":88,"courses_instructor":"karwowska, bozena","courses_title":"lit&film translt","courses_pass":10,"courses_fail":0,"courses_audit":0,"courses_uuid":"424"},{"courses_dept":"pols","courses_id":"57711","courses_avg":88,"courses_instructor":"","courses_title":"lit&film translt","courses_pass":10,"courses_fail":0,"courses_audit":0,"courses_uuid":"424"}]}