{"table":[{"courses_dept":"sowk","courses_id":"27725","courses_avg":93,"courses_instructor":"vedan, richard","courses_title":"fst ntns soc iss","courses_pass":10,"courses_fail":0,"courses_audit":0,"courses_uuid":"510"},{"courses_dept":"sowk","courses_id":"27726","courses_avg":93,"courses_instructor":"","courses_title":"fst ntns soc iss","courses_pass":10,"courses_fail":0,"courses_audit":0,"courses_uuid":"510"},{"courses_dept":"sowk","courses_id":"30668","courses_avg":87,"courses_instructor":"vedan, richard","courses_title":"fst ntns soc iss","courses_pass":8,"courses_fail":0,"courses_audit":0,"courses_uuid":"510"},{"courses_dept":"sowk","courses_id":"30669","courses_avg":87,"courses_instructor":"","courses_title":"fst ntns soc iss","courses_pass":8,"courses_fail":0,"courses_audit":0,"courses_uuid":"510"},{"courses_dept":"sowk","courses_id":"43301","courses_avg":90,"courses_instructor":"johnson, shelly","courses_title":"fst ntns soc iss","courses_pass":10,"courses_fail":0,"courses_audit":0,"courses_uuid":"510"},{"courses_dept":"sowk","courses_id":"43302","courses_avg":90,"courses_instructor":"","courses_title":"fst ntns soc iss","courses_pass":10,"courses_fail":0,"courses_audit":0,"courses_uuid":"510"},{"courses_dept":"sowk","courses_id":"71674","courses_avg":84,"courses_instructor":"johnson, shelly","courses_title":"fst ntns soc iss","courses_pass":17,"courses_fail":0,"courses_audit":0,"courses_uuid":"510"},{"courses_dept":"sowk","courses_id":"71675","courses_avg":84,"courses_instructor":"","courses_title":"fst ntns soc iss","courses_pass":18,"courses_fail":0,"courses_audit":0,"courses_uuid":"510"},{"courses_dept":"sowk","courses_id":"86025","courses_avg":82,"courses_instructor":"johnson, shelly","courses_title":"fst ntns soc iss","courses_pass":26,"courses_fail":0,"courses_audit":0,"courses_uuid":"510"},{"courses_dept":"sowk","courses_id":"86026","courses_avg":82,"courses_instructor":"","courses_title":"fst ntns soc iss","courses_pass":26,"courses_fail":0,"courses_audit":0,"courses_uuid":"510"},{"courses_dept":"sowk","courses_id":"88849","courses_avg":86,"courses_instructor":"johnson, shelly","courses_title":"fst ntns soc iss","courses_pass":22,"courses_fail":0,"courses_audit":0,"courses_uuid":"510"},{"courses_dept":"sowk","courses_id":"88850","courses_avg":86,"courses_instructor":"","courses_title":"fst ntns soc iss","courses_pass":22,"courses_fail":0,"courses_audit":0,"courses_uuid":"510"}]}